fastnode2vec/__init__.py
fastnode2vec/build_graph.py
fastnode2vec/cli.py
fastnode2vec/graph.py
fastnode2vec/node2vec.py
fastnode2vec-0.0.7.dist-info/LICENSE
fastnode2vec-0.0.7.dist-info/METADATA
fastnode2vec-0.0.7.dist-info/WHEEL
fastnode2vec-0.0.7.dist-info/entry_points.txt
fastnode2vec-0.0.7.dist-info/top_level.txt
fastnode2vec-0.0.7.dist-info/RECORD
