Metadata-Version: 2.1
Name: fastnode2vec
Version: 0.0.7
Summary: Fast implementation of node2vec
Home-page: https://github.com/louisabraham/fastnode2vec
Author: Louis Abraham
Author-email: louis.abraham@yahoo.fr
License: MIT
Classifier: Topic :: Scientific/Engineering :: Artificial Intelligence
Requires-Python: >=3.6
License-File: LICENSE
Requires-Dist: numpy
Requires-Dist: numba
Requires-Dist: gensim
Requires-Dist: click
Requires-Dist: tqdm
